pysocket/__init__.py
pysocket/client.py
pysocket/dataman.py
pysocket/server.py
py_socket-0.0.9.dist-info/LICENSE
py_socket-0.0.9.dist-info/METADATA
py_socket-0.0.9.dist-info/WHEEL
py_socket-0.0.9.dist-info/top_level.txt
py_socket-0.0.9.dist-info/RECORD
