Metadata-Version: 2.1
Name: py-socket
Version: 0.0.9
Summary: Template classes for Python socket applications.
Home-page: https://github.com/HuangPatrick16777216/pysocket
Author: Patrick Huang
Author-email: huangpatrick16777216@gmail.com
License: UNKNOWN
Platform: UNKNOWN
Classifier: Programming Language :: Python :: 3
Classifier: License :: OSI Approved :: GNU General Public License v2 or later (GPLv2+)
Classifier: Operating System :: OS Independent
Requires-Dist: cryptography
Requires-Dist: bcon
